fastapi_injectable/__init__.py
fastapi_injectable/async_exit_stack.py
fastapi_injectable/cache.py
fastapi_injectable/concurrency.py
fastapi_injectable/decorator.py
fastapi_injectable/exception.py
fastapi_injectable/logging.py
fastapi_injectable/main.py
fastapi_injectable/mypy.py
fastapi_injectable/py.typed
fastapi_injectable/util.py
fastapi_injectable_2-1.0.0.dist-info/LICENSE
fastapi_injectable_2-1.0.0.dist-info/METADATA
fastapi_injectable_2-1.0.0.dist-info/WHEEL
fastapi_injectable_2-1.0.0.dist-info/RECORD
