Metadata-Version: 2.3
Name: fastapi-injectable-2
Version: 1.0.0
Summary: Allow you to painlessly use dependency injection mechanism (`Depends`) of FastAPI outside the FastAPI routes
License: MIT
Author: Jasper Sui
Author-email: suiyang03@gmail.com
Requires-Python: >=3.10,<4.0
Classifier: Development Status :: 5 - Production/Stable
Classifier: Framework :: FastAPI
Classifier: License :: OSI Approved :: MIT License
Classifier: Programming Language :: Python :: 3
Classifier: Programming Language :: Python :: 3.10
Classifier: Programming Language :: Python :: 3.11
Classifier: Programming Language :: Python :: 3.12
Classifier: Programming Language :: Python :: 3.13
Requires-Dist: fastapi (>=0.112.4,<1.0.0)
Project-URL: Changelog, https://github.com/JasperSui/fastapi-injectable/releases
Project-URL: Documentation, https://fastapi-injectable.readthedocs.io
Project-URL: Homepage, https://github.com/JasperSui/fastapi-injectable
Project-URL: Repository, https://github.com/JasperSui/fastapi-injectable
